Workbook

Sheet R1Total
A1: TextID | B1: Perceived Authenticity | C1: Financial _Hardship | D1: Emotional _Hardship | E1: Practical _Hardship | F1: Company | G1: Authenticity evidence / notes
A2: LD01 | B2: 7 | C2: =IF(COUNTIFS('R1Counting'!$G$2:$G$540,$A2,'R1Counting'!B$2:B$540,"<>")=0,"",SUMIFS('R1Counting'!B$2:B$540,'R1Counting'!$G$2:$G$540,$A2)) -> 1 | D2: =IF(COUNTIFS('R1Counting'!$G$2:$G$540,$A2,'R1Counting'!C$2:C$540,"<>")=0,"",SUMIFS('R1Counting'!C$2:C$540,'R1Counting'!$G$2:$G$540,$A2)) -> 1 | E2: =IF(COUNTIFS('R1Counting'!$G$2:$G$540,$A2,'R1Counting'!D$2:D$540,"<>")=0,"",SUMIFS('R1Counting'!D$2:D$540,'R1Counting'!$G$2:$G$540,$A2)) -> 0 | F2: Airbnb | G2: directly references core values in the letter and holds to them in explaining each decision
A3: LD02 | B3: 6 | C3: =IF(COUNTIFS('R1Counting'!$G$2:$G$540,$A3,'R1Counting'!B$2:B$540,"<>")=0,"",SUMIFS('R1Counting'!B$2:B$540,'R1Counting'!$G$2:$G$540,$A3)) -> 0 | D3: =IF(COUNTIFS('R1Counting'!$G$2:$G$540,$A3,'R1Counting'!C$2:C$540,"<>")=0,"",SUMIFS('R1Counting'!C$2:C$540,'R1Counting'!$G$2:$G$540,$A3)) -> 3 | E3: =IF(COUNTIFS('R1Counting'!$G$2:$G$540,$A3,'R1Counting'!D$2:D$540,"<>")=0,"",SUMIFS('R1Counting'!D$2:D$540,'R1Counting'!$G$2:$G$540,$A3)) -> 2 | F3: Coinbase | G3: values are largely efficiency based, and the tone of the letter reflects that sort of coldness
A4: LD03 | B4: 3 | C4: =IF(COUNTIFS('R1Counting'!$G$2:$G$540,$A4,'R1Counting'!B$2:B$540,"<>")=0,"",SUMIFS('R1Counting'!B$2:B$540,'R1Counting'!$G$2:$G$540,$A4)) -> 0 | D4: =IF(COUNTIFS('R1Counting'!$G$2:$G$540,$A4,'R1Counting'!C$2:C$540,"<>")=0,"",SUMIFS('R1Counting'!C$2:C$540,'R1Counting'!$G$2:$G$540,$A4)) -> 1 | E4: =IF(COUNTIFS('R1Counting'!$G$2:$G$540,$A4,'R1Counting'!D$2:D$540,"<>")=0,"",SUMIFS('R1Counting'!D$2:D$540,'R1Counting'!$G$2:$G$540,$A4)) -> 2 | F4: Stripe | G4: the values are very growth oriented, and the letter reflects a degree of regret over growing too quickly
A5: LD04 | B5: 6 | C5: =IF(COUNTIFS('R1Counting'!$G$2:$G$540,$A5,'R1Counting'!B$2:B$540,"<>")=0,"",SUMIFS('R1Counting'!B$2:B$540,'R1Counting'!$G$2:$G$540,$A5)) -> 0 | D5: =IF(COUNTIFS('R1Counting'!$G$2:$G$540,$A5,'R1Counting'!C$2:C$540,"<>")=0,"",SUMIFS('R1Counting'!C$2:C$540,'R1Counting'!$G$2:$G$540,$A5)) -> 3 | E5: =IF(COUNTIFS('R1Counting'!$G$2:$G$540,$A5,'R1Counting'!D$2:D$540,"<>")=0,"",SUMIFS('R1Counting'!D$2:D$540,'R1Counting'!$G$2:$G$540,$A5)) -> 0 | F5: Shopify | G5: long term oriented values and a letter that emphasizes how that thinking led to layoffs
A6: LD05 | B6: 2 | C6: =IF(COUNTIFS('R1Counting'!$G$2:$G$540,$A6,'R1Counting'!B$2:B$540,"<>")=0,"",SUMIFS('R1Counting'!B$2:B$540,'R1Counting'!$G$2:$G$540,$A6)) -> 0 | D6: =IF(COUNTIFS('R1Counting'!$G$2:$G$540,$A6,'R1Counting'!C$2:C$540,"<>")=0,"",SUMIFS('R1Counting'!C$2:C$540,'R1Counting'!$G$2:$G$540,$A6)) -> 4 | E6: =IF(COUNTIFS('R1Counting'!$G$2:$G$540,$A6,'R1Counting'!D$2:D$540,"<>")=0,"",SUMIFS('R1Counting'!D$2:D$540,'R1Counting'!$G$2:$G$540,$A6)) -> 1 | F6: Meta | G6: no mention of values, community, connection, etc, and the letter doesn’t reflect these values either, it is largely practical
A7: LD06 | B7: 7 | C7: =IF(COUNTIFS('R1Counting'!$G$2:$G$540,$A7,'R1Counting'!B$2:B$540,"<>")=0,"",SUMIFS('R1Counting'!B$2:B$540,'R1Counting'!$G$2:$G$540,$A7)) -> 0 | D7: =IF(COUNTIFS('R1Counting'!$G$2:$G$540,$A7,'R1Counting'!C$2:C$540,"<>")=0,"",SUMIFS('R1Counting'!C$2:C$540,'R1Counting'!$G$2:$G$540,$A7)) -> 1 | E7: =IF(COUNTIFS('R1Counting'!$G$2:$G$540,$A7,'R1Counting'!D$2:D$540,"<>")=0,"",SUMIFS('R1Counting'!D$2:D$540,'R1Counting'!$G$2:$G$540,$A7)) -> 0 | F7: Microsoft | G7: direct mention of company values and leaning on them to justify decisionmaking and going forward
A8: LD07 | B8: 4 | C8: =IF(COUNTIFS('R1Counting'!$G$2:$G$540,$A8,'R1Counting'!B$2:B$540,"<>")=0,"",SUMIFS('R1Counting'!B$2:B$540,'R1Counting'!$G$2:$G$540,$A8)) -> 0 | D8: =IF(COUNTIFS('R1Counting'!$G$2:$G$540,$A8,'R1Counting'!C$2:C$540,"<>")=0,"",SUMIFS('R1Counting'!C$2:C$540,'R1Counting'!$G$2:$G$540,$A8)) -> 1 | E8: =IF(COUNTIFS('R1Counting'!$G$2:$G$540,$A8,'R1Counting'!D$2:D$540,"<>")=0,"",SUMIFS('R1Counting'!D$2:D$540,'R1Counting'!$G$2:$G$540,$A8)) -> 1 | F8: Google | G8: The letter reads very directly to shareholders and non-employees, and doesn't really feel like it is for them. Hard to say whether this aligns with the 10 things or not
A9: LD08 | B9: 6 | C9: =IF(COUNTIFS('R1Counting'!$G$2:$G$540,$A9,'R1Counting'!B$2:B$540,"<>")=0,"",SUMIFS('R1Counting'!B$2:B$540,'R1Counting'!$G$2:$G$540,$A9)) -> 0 | D9: =IF(COUNTIFS('R1Counting'!$G$2:$G$540,$A9,'R1Counting'!C$2:C$540,"<>")=0,"",SUMIFS('R1Counting'!C$2:C$540,'R1Counting'!$G$2:$G$540,$A9)) -> 1 | E9: =IF(COUNTIFS('R1Counting'!$G$2:$G$540,$A9,'R1Counting'!D$2:D$540,"<>")=0,"",SUMIFS('R1Counting'!D$2:D$540,'R1Counting'!$G$2:$G$540,$A9)) -> 0 | F9: Zoom | G9: no mention of the values, but the degree of care feels consistent with their value of care
A10: LD09 | B10: 6 | C10: =IF(COUNTIFS('R1Counting'!$G$2:$G$540,$A10,'R1Counting'!B$2:B$540,"<>")=0,"",SUMIFS('R1Counting'!B$2:B$540,'R1Counting'!$G$2:$G$540,$A10)) -> 0 | D10: =IF(COUNTIFS('R1Counting'!$G$2:$G$540,$A10,'R1Counting'!C$2:C$540,"<>")=0,"",SUMIFS('R1Counting'!C$2:C$540,'R1Counting'!$G$2:$G$540,$A10)) -> 1 | E10: =IF(COUNTIFS('R1Counting'!$G$2:$G$540,$A10,'R1Counting'!D$2:D$540,"<>")=0,"",SUMIFS('R1Counting'!D$2:D$540,'R1Counting'!$G$2:$G$540,$A10)) -> 0 | F10: Dropbox | G10: takes responsibility (core value) and emphasizes trust often (core value)
A11: LD10 | B11: 4 | C11: =IF(COUNTIFS('R1Counting'!$G$2:$G$540,$A11,'R1Counting'!B$2:B$540,"<>")=0,"",SUMIFS('R1Counting'!B$2:B$540,'R1Counting'!$G$2:$G$540,$A11)) -> 0 | D11: =IF(COUNTIFS('R1Counting'!$G$2:$G$540,$A11,'R1Counting'!C$2:C$540,"<>")=0,"",SUMIFS('R1Counting'!C$2:C$540,'R1Counting'!$G$2:$G$540,$A11)) -> 3 | E11: =IF(COUNTIFS('R1Counting'!$G$2:$G$540,$A11,'R1Counting'!D$2:D$540,"<>")=0,"",SUMIFS('R1Counting'!D$2:D$540,'R1Counting'!$G$2:$G$540,$A11)) -> 0 | F11: Spotify | G11: core values of unity and "winning together", but a layoff seems directly in conflict with that, but the letter has an action oriented looking ahead section that is aligned with their value of bias towards action

Sheet R1Counting
A1: Sentence ID | B1: Financial hardship | C1: Emotional hardship | D1: Practical hardship | E1: Notes | F1: Sentence text | G1: Article ID
A2: LD01-S001 | B2: 0 | C2: 0 | D2: 0 | F2: This is my seventh time talking to you from my house. | G2: LD01
A3: LD01-S002 | B3: 0 | C3: 0 | D3: 0 | F3: Each time we’ve talked, I’ve shared good news and bad news, but today I have to share some very sad news. | G3: LD01
A4: LD01-S003 | B4: 0 | C4: 0 | D4: 0 | F4: When you’ve asked me about layoffs, I’ve said that nothing is off the table. | G4: LD01
A5: LD01-S004 | B5: 0 | C5: 0 | D5: 0 | F5: Today, I must confirm that we are reducing the size of the Airbnb workforce. | G5: LD01
A6: LD01-S005 | B6: 0 | C6: 1 | D6: 0 | F6: For a company like us whose mission is centered around belonging, this is incredibly difficult to confront, and it will be even harder for those who have to leave Airbnb. | G6: LD01
A7: LD01-S006 | B7: 0 | C7: 0 | D7: 0 | F7: I am going to share as many details as I can on how I arrived at this decision, what we are doing for those leaving, and what will happen next. | G7: LD01
A8: LD01-S007 | B8: 0 | C8: 0 | D8: 0 | F8: Let me start with how we arrived at this decision. | G8: LD01
A9: LD01-S008 | B9: 0 | C9: 0 | D9: 0 | F9: We are collectively living through the most harrowing crisis of our lifetime, and as it began to unfold, global travel came to a standstill. | G9: LD01
A10: LD01-S009 | B10: 0 | C10: 0 | D10: 0 | F10: Airbnb’s business has been hit hard, with revenue this year forecasted to be less than half of what we earned in 2019. | G10: LD01
A11: LD01-S010 | B11: 0 | C11: 0 | D11: 0 | F11: In response, we raised $2 billion in capital and dramatically cut costs that touched nearly every corner of Airbnb. | G11: LD01
A12: LD01-S011 | B12: 0 | C12: 0 | D12: 0 | F12: While these actions were necessary, it became clear that we would have to go further when we faced two hard truths: | G12: LD01
A13: LD01-S012 | B13: 0 | C13: 0 | D13: 0 | F13: We don’t know exactly when travel will return. | G13: LD01
... A540: LD10-S057 | B540: 0 | C540: 0 | D540: 0 | F540: Just as 2023 marked a new chapter for us, so will 2024 as we build an even stronger Spotify. | G540: LD10

Sheet R2Total
A1: TextID | B1: Perceived Authenticity | C1: Financial _Hardship | D1: Emotional _Hardship | E1: Practical_Hardship | F1: Company | G1: Authenticity evidence / notes
A2: LD01 | B2: 7 | C2: =IF(COUNTIFS('R2Counting'!$G$2:$G$540,$A2,'R2Counting'!B$2:B$540,"<>")=0,"",SUMIFS('R2Counting'!B$2:B$540,'R2Counting'!$G$2:$G$540,$A2)) -> 1 | D2: =IF(COUNTIFS('R2Counting'!$G$2:$G$540,$A2,'R2Counting'!C$2:C$540,"<>")=0,"",SUMIFS('R2Counting'!C$2:C$540,'R2Counting'!$G$2:$G$540,$A2)) -> 1 | E2: =IF(COUNTIFS('R2Counting'!$G$2:$G$540,$A2,'R2Counting'!D$2:D$540,"<>")=0,"",SUMIFS('R2Counting'!D$2:D$540,'R2Counting'!$G$2:$G$540,$A2)) -> 0 | F2: Airbnb
A3: LD02 | B3: 6 | C3: =IF(COUNTIFS('R2Counting'!$G$2:$G$540,$A3,'R2Counting'!B$2:B$540,"<>")=0,"",SUMIFS('R2Counting'!B$2:B$540,'R2Counting'!$G$2:$G$540,$A3)) -> 0 | D3: =IF(COUNTIFS('R2Counting'!$G$2:$G$540,$A3,'R2Counting'!C$2:C$540,"<>")=0,"",SUMIFS('R2Counting'!C$2:C$540,'R2Counting'!$G$2:$G$540,$A3)) -> 3 | E3: =IF(COUNTIFS('R2Counting'!$G$2:$G$540,$A3,'R2Counting'!D$2:D$540,"<>")=0,"",SUMIFS('R2Counting'!D$2:D$540,'R2Counting'!$G$2:$G$540,$A3)) -> 2 | F3: Coinbase
A4: LD03 | B4: 3 | C4: =IF(COUNTIFS('R2Counting'!$G$2:$G$540,$A4,'R2Counting'!B$2:B$540,"<>")=0,"",SUMIFS('R2Counting'!B$2:B$540,'R2Counting'!$G$2:$G$540,$A4)) -> 0 | D4: =IF(COUNTIFS('R2Counting'!$G$2:$G$540,$A4,'R2Counting'!C$2:C$540,"<>")=0,"",SUMIFS('R2Counting'!C$2:C$540,'R2Counting'!$G$2:$G$540,$A4)) -> 2 | E4: =IF(COUNTIFS('R2Counting'!$G$2:$G$540,$A4,'R2Counting'!D$2:D$540,"<>")=0,"",SUMIFS('R2Counting'!D$2:D$540,'R2Counting'!$G$2:$G$540,$A4)) -> 2 | F4: Stripe
A5: LD04 | B5: 5 | C5: =IF(COUNTIFS('R2Counting'!$G$2:$G$540,$A5,'R2Counting'!B$2:B$540,"<>")=0,"",SUMIFS('R2Counting'!B$2:B$540,'R2Counting'!$G$2:$G$540,$A5)) -> 0 | D5: =IF(COUNTIFS('R2Counting'!$G$2:$G$540,$A5,'R2Counting'!C$2:C$540,"<>")=0,"",SUMIFS('R2Counting'!C$2:C$540,'R2Counting'!$G$2:$G$540,$A5)) -> 3 | E5: =IF(COUNTIFS('R2Counting'!$G$2:$G$540,$A5,'R2Counting'!D$2:D$540,"<>")=0,"",SUMIFS('R2Counting'!D$2:D$540,'R2Counting'!$G$2:$G$540,$A5)) -> 0 | F5: Shopify
A6: LD05 | B6: 2 | C6: =IF(COUNTIFS('R2Counting'!$G$2:$G$540,$A6,'R2Counting'!B$2:B$540,"<>")=0,"",SUMIFS('R2Counting'!B$2:B$540,'R2Counting'!$G$2:$G$540,$A6)) -> 0 | D6: =IF(COUNTIFS('R2Counting'!$G$2:$G$540,$A6,'R2Counting'!C$2:C$540,"<>")=0,"",SUMIFS('R2Counting'!C$2:C$540,'R2Counting'!$G$2:$G$540,$A6)) -> 4 | E6: =IF(COUNTIFS('R2Counting'!$G$2:$G$540,$A6,'R2Counting'!D$2:D$540,"<>")=0,"",SUMIFS('R2Counting'!D$2:D$540,'R2Counting'!$G$2:$G$540,$A6)) -> 1 | F6: Meta
A7: LD06 | B7: 7 | C7: =IF(COUNTIFS('R2Counting'!$G$2:$G$540,$A7,'R2Counting'!B$2:B$540,"<>")=0,"",SUMIFS('R2Counting'!B$2:B$540,'R2Counting'!$G$2:$G$540,$A7)) -> 0 | D7: =IF(COUNTIFS('R2Counting'!$G$2:$G$540,$A7,'R2Counting'!C$2:C$540,"<>")=0,"",SUMIFS('R2Counting'!C$2:C$540,'R2Counting'!$G$2:$G$540,$A7)) -> 1 | E7: =IF(COUNTIFS('R2Counting'!$G$2:$G$540,$A7,'R2Counting'!D$2:D$540,"<>")=0,"",SUMIFS('R2Counting'!D$2:D$540,'R2Counting'!$G$2:$G$540,$A7)) -> 0 | F7: Microsoft
A8: LD07 | B8: 2 | C8: =IF(COUNTIFS('R2Counting'!$G$2:$G$540,$A8,'R2Counting'!B$2:B$540,"<>")=0,"",SUMIFS('R2Counting'!B$2:B$540,'R2Counting'!$G$2:$G$540,$A8)) -> 0 | D8: =IF(COUNTIFS('R2Counting'!$G$2:$G$540,$A8,'R2Counting'!C$2:C$540,"<>")=0,"",SUMIFS('R2Counting'!C$2:C$540,'R2Counting'!$G$2:$G$540,$A8)) -> 1 | E8: =IF(COUNTIFS('R2Counting'!$G$2:$G$540,$A8,'R2Counting'!D$2:D$540,"<>")=0,"",SUMIFS('R2Counting'!D$2:D$540,'R2Counting'!$G$2:$G$540,$A8)) -> 1 | F8: Google
A9: LD08 | B9: 6 | C9: =IF(COUNTIFS('R2Counting'!$G$2:$G$540,$A9,'R2Counting'!B$2:B$540,"<>")=0,"",SUMIFS('R2Counting'!B$2:B$540,'R2Counting'!$G$2:$G$540,$A9)) -> 0 | D9: =IF(COUNTIFS('R2Counting'!$G$2:$G$540,$A9,'R2Counting'!C$2:C$540,"<>")=0,"",SUMIFS('R2Counting'!C$2:C$540,'R2Counting'!$G$2:$G$540,$A9)) -> 1 | E9: =IF(COUNTIFS('R2Counting'!$G$2:$G$540,$A9,'R2Counting'!D$2:D$540,"<>")=0,"",SUMIFS('R2Counting'!D$2:D$540,'R2Counting'!$G$2:$G$540,$A9)) -> 0 | F9: Zoom
A10: LD09 | B10: 6 | C10: =IF(COUNTIFS('R2Counting'!$G$2:$G$540,$A10,'R2Counting'!B$2:B$540,"<>")=0,"",SUMIFS('R2Counting'!B$2:B$540,'R2Counting'!$G$2:$G$540,$A10)) -> 0 | D10: =IF(COUNTIFS('R2Counting'!$G$2:$G$540,$A10,'R2Counting'!C$2:C$540,"<>")=0,"",SUMIFS('R2Counting'!C$2:C$540,'R2Counting'!$G$2:$G$540,$A10)) -> 1 | E10: =IF(COUNTIFS('R2Counting'!$G$2:$G$540,$A10,'R2Counting'!D$2:D$540,"<>")=0,"",SUMIFS('R2Counting'!D$2:D$540,'R2Counting'!$G$2:$G$540,$A10)) -> 0 | F10: Dropbox
A11: LD10 | B11: 4 | C11: =IF(COUNTIFS('R2Counting'!$G$2:$G$540,$A11,'R2Counting'!B$2:B$540,"<>")=0,"",SUMIFS('R2Counting'!B$2:B$540,'R2Counting'!$G$2:$G$540,$A11)) -> 0 | D11: =IF(COUNTIFS('R2Counting'!$G$2:$G$540,$A11,'R2Counting'!C$2:C$540,"<>")=0,"",SUMIFS('R2Counting'!C$2:C$540,'R2Counting'!$G$2:$G$540,$A11)) -> 3 | E11: =IF(COUNTIFS('R2Counting'!$G$2:$G$540,$A11,'R2Counting'!D$2:D$540,"<>")=0,"",SUMIFS('R2Counting'!D$2:D$540,'R2Counting'!$G$2:$G$540,$A11)) -> 0 | F11: Spotify

Sheet R2Counting
A1: Sentence ID | B1: Financial hardship | C1: Emotional hardship | D1: Practical hardship | E1: Notes | F1: Sentence text | G1: Article ID
A2: LD01-S001 | B2: 0 | C2: 0 | D2: 0 | F2: This is my seventh time talking to you from my house. | G2: LD01
A3: LD01-S002 | B3: 0 | C3: 0 | D3: 0 | F3: Each time we’ve talked, I’ve shared good news and bad news, but today I have to share some very sad news. | G3: LD01
A4: LD01-S003 | B4: 0 | C4: 0 | D4: 0 | F4: When you’ve asked me about layoffs, I’ve said that nothing is off the table. | G4: LD01
A5: LD01-S004 | B5: 0 | C5: 0 | D5: 0 | F5: Today, I must confirm that we are reducing the size of the Airbnb workforce. | G5: LD01
A6: LD01-S005 | B6: 0 | C6: 1 | D6: 0 | F6: For a company like us whose mission is centered around belonging, this is incredibly difficult to confront, and it will be even harder for those who have to leave Airbnb. | G6: LD01
A7: LD01-S006 | B7: 0 | C7: 0 | D7: 0 | F7: I am going to share as many details as I can on how I arrived at this decision, what we are doing for those leaving, and what will happen next. | G7: LD01
A8: LD01-S007 | B8: 0 | C8: 0 | D8: 0 | F8: Let me start with how we arrived at this decision. | G8: LD01
A9: LD01-S008 | B9: 0 | C9: 0 | D9: 0 | F9: We are collectively living through the most harrowing crisis of our lifetime, and as it began to unfold, global travel came to a standstill. | G9: LD01
A10: LD01-S009 | B10: 0 | C10: 0 | D10: 0 | F10: Airbnb’s business has been hit hard, with revenue this year forecasted to be less than half of what we earned in 2019. | G10: LD01
A11: LD01-S010 | B11: 0 | C11: 0 | D11: 0 | F11: In response, we raised $2 billion in capital and dramatically cut costs that touched nearly every corner of Airbnb. | G11: LD01
A12: LD01-S011 | B12: 0 | C12: 0 | D12: 0 | F12: While these actions were necessary, it became clear that we would have to go further when we faced two hard truths: | G12: LD01
A13: LD01-S012 | B13: 0 | C13: 0 | D13: 0 | F13: We don’t know exactly when travel will return. | G13: LD01
... A540: LD10-S057 | B540: 0 | C540: 0 | D540: 0 | F540: Just as 2023 marked a new chapter for us, so will 2024 as we build an even stronger Spotify. | G540: LD10
